pymine_server/__init__.py
pymine_server-0.0.0.dist-info/WHEEL
pymine_server-0.0.0.dist-info/METADATA
pymine_server-0.0.0.dist-info/RECORD
