Metadata-Version: 2.1
Name: pymine-server
Version: 0.0.0
Summary: A fast and easy to use, moddable, Python based Minecraft server!
Author: Milo Weinberg
Author-email: iapetus011@gmail.com
Requires-Python: >=3.9,<4.0
Classifier: Programming Language :: Python :: 3
Classifier: Programming Language :: Python :: 3.10
Classifier: Programming Language :: Python :: 3.9
